image_zoom_lens/__init__.py
image_zoom_lens/frontend/index.html
image_zoom_lens-0.1.0.dist-info/licenses/LICENSE
image_zoom_lens-0.1.0.dist-info/METADATA
image_zoom_lens-0.1.0.dist-info/WHEEL
image_zoom_lens-0.1.0.dist-info/top_level.txt
image_zoom_lens-0.1.0.dist-info/RECORD
