Metadata-Version: 2.4
Name: image_zoom_lens
Version: 0.1.0
Summary: A Streamlit component for interactive image zoom with movable lens
Author-email: Abhijit Majumdar <abhijit.g.majumdar@gmail.com>
License: MIT
Project-URL: Homepage, https://github.com/abhijitmajumdar/image_zoom_lens
Keywords: streamlit,component,image,zoom,lens
Requires-Python: >=3.7
License-File: LICENSE
Requires-Dist: streamlit>=1.28.0
Provides-Extra: dev
Requires-Dist: ruff>=0.1.0; extra == "dev"
Requires-Dist: pre-commit>=3.0.0; extra == "dev"
Dynamic: license-file
